setup.py
walkdict.py
walkdict.egg-info/PKG-INFO
walkdict.egg-info/SOURCES.txt
walkdict.egg-info/dependency_links.txt
walkdict.egg-info/top_level.txt