Metadata-Version: 1.0
Name: walkdict
Version: 1.0
Summary: deep traverse dict or list
Home-page: https://github.com/guyskk/walkdict
Author: kk
Author-email: UNKNOWN
License: MIT
Platform: UNKNOWN
